MANIFEST.in
setup.py
src/schettino.py
src/problems/__init__.py
src/problems/base.py
src/problems/complex.py
src/problems/file.py
src/problems/simple.py
src/schettino.egg-info/PKG-INFO
src/schettino.egg-info/SOURCES.txt
src/schettino.egg-info/dependency_links.txt
src/schettino.egg-info/not-zip-safe
src/schettino.egg-info/requires.txt
src/schettino.egg-info/top_level.txt